README.md
setup.py
WebImageDowloader/__init__.py
WebImageDowloader/main.py
WebImageDowloader.egg-info/PKG-INFO
WebImageDowloader.egg-info/SOURCES.txt
WebImageDowloader.egg-info/dependency_links.txt
WebImageDowloader.egg-info/requires.txt
WebImageDowloader.egg-info/top_level.txt