Metadata-Version: 2.1
Name: WebImageDowloader
Version: 0.1
Summary: Python library to download images from a URL
Home-page: UNKNOWN
Author: Raheel Asghar Ghauri
Author-email: raheelghauri786@hotmail.com
License: UNKNOWN
Platform: UNKNOWN
